covsonar/__init__.py
covsonar/align.py
covsonar/basics.py
covsonar/cache.py
covsonar/data/EDNAFULL
covsonar/data/db.sqlite
covsonar/data/db.sqlite.old
covsonar/data/doctest_b117.fna
covsonar/data/doctest_b117.pickle
covsonar/data/paranoid.alignment.fna
covsonar/data/ref.fna
covsonar/data/ref.gb
covsonar/data/ref.gff3
covsonar/dbm.py
covsonar/linmgr.py
covsonar/sonar.py
covsonar/sonardb.py
covsonar-2.0.0a1.dist-info/entry_points.txt
covsonar-2.0.0a1.dist-info/LICENSE
covsonar-2.0.0a1.dist-info/WHEEL
covsonar-2.0.0a1.dist-info/METADATA
covsonar-2.0.0a1.dist-info/RECORD
