Metadata-Version: 2.1
Name: covsonar
Version: 2.0.0a1
Summary: A database-driven system for handling genomic sequences and screening genomic profiles.
Home-page: https://github.com/rki-mf1/covsonar
License: GPL3
Author: Stephan Fuchs
Author-email: FuchsS@rki.de
Requires-Python: >=3.9,<4.0
Classifier: License :: Other/Proprietary License
Classifier: Programming Language :: Python :: 3
Classifier: Programming Language :: Python :: 3.10
Classifier: Programming Language :: Python :: 3.9
Requires-Dist: biopython (>=1.79,<1.80)
Requires-Dist: more-itertools (>=8.7.0,<8.8.0)
Requires-Dist: mpire (>=2.3.3,<2.4.0)
Requires-Dist: pandas (>=1.4.0,<1.5.0)
Requires-Dist: pyaml (>=20.4.0,<20.5.0)
Requires-Dist: requests (>=2.28.0,<3.0.0)
Requires-Dist: tabulate (>=0.8.9,<0.9.0)
Requires-Dist: tqdm (>=4.59.0,<4.60.0)
Project-URL: Repository, https://github.com/rki-mf1/covsonar
